jhub_authenticators-0.6.1.dist-info/licenses/LICENCE.txt
jhubauthenticators/__init__.py
jhubauthenticators/_dummy_auth.py
jhubauthenticators/_jhub_header_auth.py
jhubauthenticators/_jhub_remote_auth.py
jhubauthenticators/_jhub_shared.py
jhubauthenticators/_version.py
jhub_authenticators-0.6.1.dist-info/METADATA
jhub_authenticators-0.6.1.dist-info/WHEEL
jhub_authenticators-0.6.1.dist-info/top_level.txt
jhub_authenticators-0.6.1.dist-info/RECORD
