Metadata-Version: 2.4
Name: jhub-authenticators
Version: 0.6.1
Summary: A collection of HTTP(s) JupyterHub Header Authenticators,including a Header, and Dummy authenticator
Home-page: https://github.com/ucphhpc/jhub-authenticators
Author: Rasmus Munk
Author-email: munk1@live.dk
License: GNU General Public License v2 (GPLv2)
Project-URL: Source Code, https://github.com/ucphhpc/jhub-authenticators
Keywords: Interactive,Interpreter,Shell,Web
Platform: Linux
Platform: Mac OSX
Classifier: Intended Audience :: Developers
Classifier: Intended Audience :: System Administrators
Classifier: Intended Audience :: Science/Research
Classifier: Programming Language :: Python :: 3.9
Classifier: Programming Language :: Python :: 3.10
Classifier: Programming Language :: Python :: 3.11
Classifier: Programming Language :: Python :: 3.12
License-File: LICENCE.txt
Requires-Dist: jupyterhub>5.1.0
Provides-Extra: test
Requires-Dist: pytest>=7.4.4; extra == "test"
Requires-Dist: docker>=7.1.0; extra == "test"
Requires-Dist: six>=1.16.0; extra == "test"
Requires-Dist: docutils>=0.21.2; extra == "test"
Provides-Extra: dev
Requires-Dist: black==24.10.0; extra == "dev"
Requires-Dist: docutils>=0.21.2; extra == "dev"
Requires-Dist: flake8>=7.1.2; extra == "dev"
Requires-Dist: Click>=8.2.0; extra == "dev"
Dynamic: author
Dynamic: author-email
Dynamic: classifier
Dynamic: description
Dynamic: home-page
Dynamic: keywords
Dynamic: license
Dynamic: license-file
Dynamic: platform
Dynamic: project-url
Dynamic: provides-extra
Dynamic: requires-dist
Dynamic: summary
